{
  "ui:grid": [
    {
      "collection": 8,
      "title": 16
    },
    {
      "data_type": 4,
      "stac_version": 4,
      "license": 4,
      "dashboard:is_periodic": 2,
      "dashboard:time_density": 4,
      "dashboard:time_interval": 6
    },
    {
      "description": 12,
      "spatial_extent": 6,
      "temporal_extent": 6
    },
    {
      "discovery_items": 24
    },
    {
      "sample_files": 24
    },
    {
      "renders": 12,
      "stac_extensions": 12
    },
    {
      "links": 24
    },
    {
      "item_assets": 24
    },
    {
      "providers": 24
    }
  ],
  "spatial_extent": {
    "ui:grid": [
      {
        "xmin": 12,
        "ymin": 12
      },
      {
        "xmax": 12,
        "ymax": 12
      }
    ]
  },
  "discovery_items": {
    "items": {
      "datetime_range": {
        "ui:help": "omit for sub-daily data"
      },
      "filename_regex": {
        "ui:widget": "regexString"
      },
      "id_regex": {
        "ui:widget": "regexString"
      },
      "ui:grid": [
        {
          "discovery": 8,
          "prefix": 8,
          "bucket": 8
        },
        {
          "filename_regex": 24
        },
        {
          "stac_extensions": 12,
          "links": 12
        },
        {
          "datetime_range": 6,
          "start_datetime": 6,
          "end_datetime": 6,
          "single_datetime": 6
        },
        {
          "id_regex": 8,
          "id_template": 8,
          "use_multithreading": 8
        },
        {
          "disasters:extract_event_name": 6,
          "disasters:monty": 6,
          "disasters:add_product": 6,
          "disasters:add_providers": 6
        },
        {
          "cogify": 12,
          "dry_run": 12
        },
        {
          "assets": 24
        }
      ],
      "assets": {
        "ui:additionalProperties": {
          "ui:grid": [
            {
              "title": 12,
              "regex": 12
            },
            {
              "description": 24
            }
          ],
          "description": {
            "ui:widget": "textarea",
            "ui:options": {
              "rows": 4
            }
          }
        }
      }
    }
  },
  "links": {
    "items": {
      "ui:grid": [
        {
          "href": 12,
          "rel": 12
        },
        {
          "type": 12,
          "title": 12
        },
        {
          "label:assets": 12
        }
      ]
    }
  },
  "item_assets": {
    "ColorIR": {
      "ui:grid": [
        {
          "title": 12,
          "type": 12
        },
        {
          "description": 12,
          "roles": 12
        }
      ],
      "description": {
        "ui:widget": "textarea",
        "ui:options": {
          "rows": 4
        }
      }
    },
    "ui:additionalProperties": {
      "ui:grid": [
        {
          "title": 12,
          "type": 12
        },
        {
          "description": 12,
          "roles": 12
        }
      ],
      "description": {
        "ui:widget": "textarea",
        "ui:options": {
          "rows": 4
        }
      }
    }
  },
  "providers": {
    "items": {
      "ui:grid": [
        {
          "name": 12,
          "description": 12
        },
        {
          "roles": 12,
          "url": 12
        }
      ]
    }
  },
  "description": {
    "ui:widget": "textarea",
    "ui:options": {
      "rows": 8,
      "description": "This describes the dataset."
    }
  },
  "renders": {
    "dashboard": {
      "ui:widget": "renders.dashboard",
      "ui:options": {
        "rows": 12
      }
    },
    "ColorIR": {
      "ui:widget": "renders.dashboard",
      "ui:options": {
        "rows": 12
      }
    },
    "ui:classNames": "renders"
  },
  "temporal_extent": {
    "startdate": {
      "ui:widget": "text"
    },
    "enddate": {
      "ui:widget": "text"
    }
  },
  "ui:submitButtonOptions": {
    "props": {
      "color": "primary",
      "variant": "solid",
      "size": "large",
      "block": "true"
    }
  },
  "sample_files": {
    "items": {
      "ui:widget": "testableUrl"
    }
  }
}
